MANIFEST.in
README.txt
bootstrap.py
buildout.cfg
setup.py
collective/__init__.py
collective.js.cufon.egg-info/PKG-INFO
collective.js.cufon.egg-info/SOURCES.txt
collective.js.cufon.egg-info/dependency_links.txt
collective.js.cufon.egg-info/entry_points.txt
collective.js.cufon.egg-info/namespace_packages.txt
collective.js.cufon.egg-info/not-zip-safe
collective.js.cufon.egg-info/requires.txt
collective.js.cufon.egg-info/top_level.txt
collective/js/__init__.py
collective/js/cufon/Vegur.font.js
collective/js/cufon/__init__.py
collective/js/cufon/configure.zcml
collective/js/cufon/cufon-1.09i.js
collective/js/cufon/example.pt
collective/js/cufon/example.py
collective/js/cufon/profiles/default/jsregistry.xml
collective/js/cufon/profiles/default/metadata.xml
docs/HISTORY.txt