Metadata-Version: 1.0
Name: collective.js.cufon
Version: 1.09i.1
Summary: Cufon aims to become a worthy alternative to sIFR
Home-page: https://github.com/collective/collective.js.cufon
Author: JeanMichel FRANCOIS aka toutpt
Author-email: toutpt@gmail.com
License: GPL
Platform: UNKNOWN
Classifier: Programming Language :: Python
